gptop/__init__.py
gptop/config.py
gptop/operation.py
gptop/operation_utils.py
gptop/operator.py
gptop/utils.py
gptop/operations/__init__.py
gptop/operations/command.py
gptop/operations/download.py
gptop/operations/file.py
gptop/operations/http.py
gptop-0.0.7.dist-info/LICENSE
gptop-0.0.7.dist-info/METADATA
gptop-0.0.7.dist-info/WHEEL
gptop-0.0.7.dist-info/top_level.txt
gptop-0.0.7.dist-info/RECORD
