Metadata-Version: 2.1
Name: gptop
Version: 0.0.7
Summary: Handles communication with GPTs
Home-page: https://github.com/ncrews35/gpt-operator
Author: Nick Crews
Author-email: nickcrews35@gmail.com
Keywords: gptop GPT operator llm ai
Classifier: Development Status :: 5 - Production/Stable
Classifier: Intended Audience :: Developers
Classifier: License :: OSI Approved :: MIT License
Classifier: Operating System :: OS Independent
Classifier: Programming Language :: Python :: 3
Classifier: Programming Language :: Python :: 3.6
Classifier: Programming Language :: Python :: 3.7
Classifier: Programming Language :: Python :: 3.8
Classifier: Programming Language :: Python :: 3.9
Requires-Python: >=3.6
License-File: LICENSE
Requires-Dist: requests (>=2.20)
Requires-Dist: scikit-learn (>=1.0.2)
Requires-Dist: tenacity (>=8.0.1)
Requires-Dist: matplotlib
Requires-Dist: plotly
Requires-Dist: numpy
Requires-Dist: scipy
Requires-Dist: pandas (>=1.2.3)
Requires-Dist: pandas-stubs (>=1.1.0.11)
Requires-Dist: openpyxl (>=3.0.7)
Requires-Dist: aiohttp
Requires-Dist: tqdm
Requires-Dist: pyyaml (>=5.4)
Requires-Dist: loguru (>=0.5.0)
Requires-Dist: typing-extensions (>=3.7.4)
Requires-Dist: dnspython (>=2.0.0)
Requires-Dist: python-dateutil (>=2.5.3)
Requires-Dist: urllib3 (>=1.21.1)
Requires-Dist: openai
Requires-Dist: pinecone-client
Provides-Extra: dev
Requires-Dist: pytest ; extra == 'dev'
Requires-Dist: pytest-cov ; extra == 'dev'
Requires-Dist: flake8 ; extra == 'dev'
Requires-Dist: black ; extra == 'dev'
Requires-Dist: isort ; extra == 'dev'
Requires-Dist: mypy ; extra == 'dev'
Requires-Dist: pre-commit ; extra == 'dev'
